arbitbot/__init__.py
arbitbot/detector.py
arbitbot-0.2.2.dist-info/licenses/LICENSE
arbitbot-0.2.2.dist-info/METADATA
arbitbot-0.2.2.dist-info/WHEEL
arbitbot-0.2.2.dist-info/top_level.txt
arbitbot-0.2.2.dist-info/RECORD
