Metadata-Version: 2.4
Name: arbitbot
Version: 0.2.2
Summary: Simple multi-exchange crypto arbitrage detector
Home-page: https://github.com/Hung-Ching-Lee/Arbitbot
Author: Hung-Ching-Lee
License: MIT
Requires-Python: >=3.8
License-File: LICENSE
Dynamic: home-page
Dynamic: license-file
Dynamic: requires-python
